phlash/__init__.py
phlash/_version.py
phlash/afs.py
phlash/base.py
phlash/cband.py
phlash/conftest.py
phlash/data/ts.py
phlash/data/vcf.py
phlash/data.py
phlash/gpu.py
phlash/hmm.py
phlash/jax_ppoly.py
phlash/kernel.py
phlash/ld/svgp.py
phlash/likelihood/__init__.py
phlash/likelihood/afs.py
phlash/likelihood/seq.py
phlash/liveplot.py
phlash/mcmc.py
phlash/methods/phlash.py
phlash/model.py
phlash/models/__init__.py
phlash/models/demes.py
phlash/models/panmictic.py
phlash/mp.py
phlash/params.py
phlash/plot.py
phlash/psmc.py
phlash/runner.py
phlash/sample.icf/ALT/p0/2
phlash/sample.icf/ALT/p0/chunk_index
phlash/sample.icf/ALT/p1/6
phlash/sample.icf/ALT/p1/chunk_index
phlash/sample.icf/ALT/p2/1
phlash/sample.icf/ALT/p2/chunk_index
phlash/sample.icf/CHROM/p0/2
phlash/sample.icf/CHROM/p0/chunk_index
phlash/sample.icf/CHROM/p1/6
phlash/sample.icf/CHROM/p1/chunk_index
phlash/sample.icf/CHROM/p2/1
phlash/sample.icf/CHROM/p2/chunk_index
phlash/sample.icf/FILTERS/p0/2
phlash/sample.icf/FILTERS/p0/chunk_index
phlash/sample.icf/FILTERS/p1/6
phlash/sample.icf/FILTERS/p1/chunk_index
phlash/sample.icf/FILTERS/p2/1
phlash/sample.icf/FILTERS/p2/chunk_index
phlash/sample.icf/FORMAT/DP/p0/2
phlash/sample.icf/FORMAT/DP/p0/chunk_index
phlash/sample.icf/FORMAT/DP/p1/6
phlash/sample.icf/FORMAT/DP/p1/chunk_index
phlash/sample.icf/FORMAT/DP/p2/1
phlash/sample.icf/FORMAT/DP/p2/chunk_index
phlash/sample.icf/FORMAT/GQ/p0/2
phlash/sample.icf/FORMAT/GQ/p0/chunk_index
phlash/sample.icf/FORMAT/GQ/p1/6
phlash/sample.icf/FORMAT/GQ/p1/chunk_index
phlash/sample.icf/FORMAT/GQ/p2/1
phlash/sample.icf/FORMAT/GQ/p2/chunk_index
phlash/sample.icf/FORMAT/GT/p0/2
phlash/sample.icf/FORMAT/GT/p0/chunk_index
phlash/sample.icf/FORMAT/GT/p1/6
phlash/sample.icf/FORMAT/GT/p1/chunk_index
phlash/sample.icf/FORMAT/GT/p2/1
phlash/sample.icf/FORMAT/GT/p2/chunk_index
phlash/sample.icf/FORMAT/HQ/p0/2
phlash/sample.icf/FORMAT/HQ/p0/chunk_index
phlash/sample.icf/FORMAT/HQ/p1/6
phlash/sample.icf/FORMAT/HQ/p1/chunk_index
phlash-1.0.6.dist-info/WHEEL
phlash-1.0.6.dist-info/METADATA
phlash-1.0.6.dist-info/RECORD
