Metadata-Version: 2.3
Name: phlash
Version: 1.0.6
Summary: Bayesian inference of population size history from recombining sequence data.
Author: Jonathan Terhorst
Author-email: Jonathan Terhorst <jonth@umich.edu>
License: MIT
Requires-Dist: blackjax>=1.1.0,<2.0.0
Requires-Dist: intervaltree>=3.1.0,<4.0.0
Requires-Dist: jax>=0.4.25,<0.6.0
Requires-Dist: loguru>=0.7.2,<1.0.0
Requires-Dist: matplotlib>=3.8.2,<4.0.0
Requires-Dist: msprime>=1.3.2
Requires-Dist: numpy>1.25
Requires-Dist: optax>=0.1.9,<1.0.0
Requires-Dist: plotly>=6
Requires-Dist: scipy>=1.12.0,<2.0.0
Requires-Dist: stdpopsim>=0.2.0,<1.0.0
Requires-Dist: tqdm>=4.66.1,<5.0.0
Requires-Dist: tskit>=0.5.8
Requires-Dist: demes>=0.2.3,<1.0.0
Requires-Dist: jax-dataclasses>=1.6.0,<2.0.0
Requires-Dist: tszip>=0.2.3,<1.0.0
Requires-Dist: jaxtyping>=0.2.25,<1.0.0
Requires-Dist: pulp>=2.8.0
Requires-Dist: pysam>=0.22.1
Requires-Dist: scienceplots>=2.1.1
Requires-Dist: numcodecs<0.16
Requires-Dist: jax[cuda12]>=0.4.25,<0.6.0 ; extra == 'gpu'
Requires-Dist: cuda-python>=12.3,<13 ; extra == 'gpu'
Requires-Dist: nvidia-cuda-nvrtc-cu12>=12.3 ; extra == 'gpu'
Requires-Python: >=3.12, <4.0
Project-URL: Bug Reports, https://github.com/jthlab/phlash/issues
Project-URL: Homepage, https://github.com/jthlab/phlash
Project-URL: Source, https://github.com/jthlab/phlash/
Provides-Extra: gpu
